integration_test/__init__.py
integration_test/conftest.py
integration_test/test_datetime.py
integration_test/test_dict_util.py
integration_test/test_github.py
integration_test/test_integration.py
integration_test/test_timer.py
integration_test/test_urlencode.py
integration_test/test_wrappers.py
integration_test/test_yaml_util.py
nbdev_template/__init__.py
nbdev_template/_nbdev.py
nicHelper/__init__.py
nicHelper/_nbdev.py
nicHelper/async.py
nicHelper/asyncUtil.py
nicHelper/awsutil.py
nicHelper/cloudfront.py
nicHelper/colab.py
nicHelper/compress.py
nicHelper/dataclassUtil.py
nicHelper/datetime.py
nicHelper/dictUtil.py
nicHelper/distance.py
nicHelper/encrypt.py
nicHelper/exception.py
nicHelper/github.py
nicHelper/images.py
nicHelper/jsonUtil.py
nicHelper/jupyter.py
nicHelper/pdUtils.py
nicHelper/pynamodb.py
nicHelper/pynamodbAttributes.py
nicHelper/rsa.py
nicHelper/schema.py
nicHelper/secrets.py
nicHelper/sentryUtil.py
nicHelper/shortenLink.py
nicHelper/string.py
nicHelper/timer.py
nicHelper/urlencode.py
nicHelper/wrappers.py
nicHelper/yamlUtil.py
tests/__init__.py
tests/conftest.py
tests/test_dict_util.py
tests/test_github.py
tests/test_integration.py
tests/test_pynamodb.py
tests/test_rsa.py
tests/test_timer.py
tests/test_wrappers.py
tests/test_yaml_util.py
tests/nicHelper/__init__.py
tests/nicHelper/_nbdev.py
tests/nicHelper/async.py
tests/nicHelper/asyncUtil.py
tests/nicHelper/awsutil.py
tests/nicHelper/cloudfront.py
tests/nicHelper/colab.py
tests/nicHelper/compress.py
tests/nicHelper/dataclassUtil.py
tests/nicHelper/datetime.py
tests/nicHelper/dictUtil.py
tests/nicHelper/distance.py
tests/nicHelper/encrypt.py
tests/nicHelper/exception.py
tests/nicHelper/github.py
tests/nicHelper/images.py
tests/nicHelper/jsonUtil.py
tests/nicHelper/jupyter.py
tests/nicHelper/pdUtils.py
tests/nicHelper/pynamodb.py
tests/nicHelper/pynamodbAttributes.py
tests/nicHelper/rsa.py
tests/nicHelper/schema.py
tests/nicHelper/secrets.py
tests/nicHelper/sentryUtil.py
nicHelper-0.0.123.dist-info/LICENSE
nicHelper-0.0.123.dist-info/METADATA
nicHelper-0.0.123.dist-info/WHEEL
nicHelper-0.0.123.dist-info/entry_points.txt
nicHelper-0.0.123.dist-info/top_level.txt
nicHelper-0.0.123.dist-info/RECORD
