Metadata-Version: 2.1
Name: nicHelper
Version: 0.0.123
Summary: some helper functions from nic's gist
Home-page: https://github.com/thanakijwanavit/nicHelper/tree/master/
Author: nic wanavit
Author-email: nwanavit@hatari.cc
License: Apache Software License 2.0
Keywords: nicHelper
Platform: UNKNOWN
Classifier: Development Status :: 3 - Alpha
Classifier: Intended Audience :: Developers
Classifier: License :: OSI Approved :: Apache Software License
Classifier: Natural Language :: English
Classifier: Programming Language :: Python :: 3.6
Classifier: Programming Language :: Python :: 3.7
Classifier: Programming Language :: Python :: 3.8
Requires-Python: >=3.6
Requires-Dist: requests
Requires-Dist: boto3
Requires-Dist: ujson
Requires-Dist: Pillow
Requires-Dist: genson
Requires-Dist: pyyaml
Requires-Dist: dpath
Requires-Dist: pytest
Requires-Dist: beartype
Requires-Dist: dataclasses-jsonschema
Requires-Dist: cachetools
Requires-Dist: pycryptodome
